setup.py
pyanalytics/__init__.py
pyanalytics/entities.py
pyanalytics/requests.py
pyanalytics/utils.py
pyanalytics.egg-info/PKG-INFO
pyanalytics.egg-info/SOURCES.txt
pyanalytics.egg-info/dependency_links.txt
pyanalytics.egg-info/top_level.txt