Metadata-Version: 1.1
Name: pyanalytics
Version: 0.0.1
Summary: Google Analytics collection api - now use it in server as well (not just client). You can track your server side  request / API request which are not possible using client js of Google Analytics.
Home-page: https://github.com/zonito/pyanalytics
Author: Love Sharma
Author-email: contact@lovesharma.com
License: MIT
Download-URL: https://github.com/zonito/pyanalytics/archive/0.0.1.tar.gz
Keywords: google,analytics,pyanalytics,python,track,server,client,api
Platform: UNKNOWN
